[
  {
    "image": "store",
    "sha": "88d638b",
    "digest": "sha256:dd3299fb36e4323dc4bd0f9eed490c4dab3bbb32fb94b0b94e04422f0c8f9c94",
    "run_id": "28903006103",
    "run_number": 230,
    "run_url": "https://github.com/\\lmthing/lmthing/actions/runs/28903006103",
    "status": "completed",
    "conclusion": "success",
    "updated_at": "2026-07-07T22:29:42.960198+00:00"
  },
  {
    "image": "store",
    "sha": "c8a9c15",
    "digest": "sha256:b3f4cf92a0d2b4b433354ad7b2dad4c3d92677a024c2e5cf022ede4082ca9555",
    "run_id": "28902077694",
    "run_number": 229,
    "run_url": "https://github.com/\\lmthing/lmthing/actions/runs/28902077694",
    "status": "completed",
    "conclusion": "success",
    "updated_at": "2026-07-07T22:09:49.760359+00:00"
  },
  {
    "image": "store",
    "sha": "ddddd85",
    "digest": "sha256:3ee106ed9bfa0d08877ea6bcc450093224eaf1c78d76c64be2692c27105eb24f",
    "run_id": "28901924755",
    "run_number": 227,
    "run_url": "https://github.com/\\lmthing/lmthing/actions/runs/28901924755",
    "status": "completed",
    "conclusion": "success",
    "updated_at": "2026-07-07T22:06:51.259096+00:00"
  },
  {
    "image": "store",
    "sha": "1389d1a",
    "digest": "sha256:b9568223afe62c21938c06a084601bbfeeb1dc207c10f36d89fa6dda473eafa0",
    "run_id": "28901594760",
    "run_number": 226,
    "run_url": "https://github.com/\\lmthing/lmthing/actions/runs/28901594760",
    "status": "completed",
    "conclusion": "success",
    "updated_at": "2026-07-07T22:00:48.695212+00:00"
  },
  {
    "image": "store",
    "sha": "933ffc4",
    "digest": "sha256:6a3179bba06c6ba9765d0708710460f775d31d453892c393cd55f5f59ab04216",
    "run_id": "28901307758",
    "run_number": 224,
    "run_url": "https://github.com/\\lmthing/lmthing/actions/runs/28901307758",
    "status": "completed",
    "conclusion": "success",
    "updated_at": "2026-07-07T21:55:09.062294+00:00"
  },
  {
    "image": "store",
    "sha": "ff79155",
    "digest": "sha256:8293acacb7de333556112e25ff3c1fd8ba1c633d87eed5b419dff0a439e4c539",
    "run_id": "28900949414",
    "run_number": 223,
    "run_url": "https://github.com/\\lmthing/lmthing/actions/runs/28900949414",
    "status": "completed",
    "conclusion": "success",
    "updated_at": "2026-07-07T21:48:33.659840+00:00"
  },
  {
    "image": "store",
    "sha": "4fbd1cf",
    "digest": "sha256:a1045c9536209c8089f349abf175ad833a2962409ff3bff0646d473520d5a58e",
    "run_id": "28885958817",
    "run_number": 222,
    "run_url": "https://github.com/\\lmthing/lmthing/actions/runs/28885958817",
    "status": "completed",
    "conclusion": "success",
    "updated_at": "2026-07-07T17:35:06.963836+00:00"
  },
  {
    "image": "store",
    "sha": "2abca27",
    "digest": "sha256:b1733d229770dff9cb4d6c893edb3f53837752915a17e3eae73876ebe5f1f228",
    "run_id": "28885836549",
    "run_number": 220,
    "run_url": "https://github.com/\\lmthing/lmthing/actions/runs/28885836549",
    "status": "completed",
    "conclusion": "success",
    "updated_at": "2026-07-07T17:31:20.809320+00:00"
  },
  {
    "image": "store",
    "sha": "0eaed33",
    "digest": "sha256:32109935c2d55225e198e396d207e2523304860d8bf5418b1c63c4aebe10a919",
    "run_id": "28885648633",
    "run_number": 219,
    "run_url": "https://github.com/\\lmthing/lmthing/actions/runs/28885648633",
    "status": "completed",
    "conclusion": "success",
    "updated_at": "2026-07-07T17:27:58.636712+00:00"
  },
  {
    "image": "store",
    "sha": "aa3e368",
    "digest": "sha256:dfc2821d771aeae200b07f8db945e65ff5038c0288664f36ef13bc6b1cef0dc6",
    "run_id": "28884447937",
    "run_number": 218,
    "run_url": "https://github.com/\\lmthing/lmthing/actions/runs/28884447937",
    "status": "completed",
    "conclusion": "success",
    "updated_at": "2026-07-07T17:08:04.971300+00:00"
  },
  {
    "image": "store",
    "sha": "d4dc790",
    "digest": "sha256:d390f2677b341aca096d036ce34ef7b12515e05161a114f5441249a9546f2aa7",
    "run_id": "28883019040",
    "run_number": 217,
    "run_url": "https://github.com/\\lmthing/lmthing/actions/runs/28883019040",
    "status": "completed",
    "conclusion": "success",
    "updated_at": "2026-07-07T16:45:18.679062+00:00"
  },
  {
    "image": "store",
    "sha": "1e79b6f",
    "digest": "sha256:4f01f52feed1ba2424042a85b02ffbee984d1bbd541e70443c5a27f376fd5a77",
    "run_id": "28880461394",
    "run_number": 216,
    "run_url": "https://github.com/\\lmthing/lmthing/actions/runs/28880461394",
    "status": "completed",
    "conclusion": "success",
    "updated_at": "2026-07-07T16:04:01.590416+00:00"
  },
  {
    "image": "store",
    "sha": "c6a0423",
    "digest": "sha256:a078d43067930abd0ddba5a26103ff327ea5e0d31debbafa2e748e3bd082ad87",
    "run_id": "28878635716",
    "run_number": 215,
    "run_url": "https://github.com/\\lmthing/lmthing/actions/runs/28878635716",
    "status": "completed",
    "conclusion": "success",
    "updated_at": "2026-07-07T15:36:24.331568+00:00"
  },
  {
    "image": "gateway",
    "sha": "0124f64",
    "digest": "sha256:d13b33c1289bdf6914aa549fe42a2539cc8492c7fe6ea0bcdbff9993f5387236",
    "run_id": "28842641848",
    "run_number": 214,
    "run_url": "https://github.com/\\lmthing/lmthing/actions/runs/28842641848",
    "status": "completed",
    "conclusion": "success",
    "updated_at": "2026-07-07T04:58:34.163412+00:00"
  },
  {
    "image": "team",
    "sha": "c9e53f0",
    "digest": "sha256:6781c4b0236350d9a7468bfca626582c295dccbf082ed1c9d89968f3c503ff90",
    "run_id": "28826217268",
    "run_number": 213,
    "run_url": "https://github.com/\\lmthing/lmthing/actions/runs/28826217268",
    "status": "completed",
    "conclusion": "success",
    "updated_at": "2026-07-06T22:02:01.546397+00:00"
  },
  {
    "image": "space",
    "sha": "c9e53f0",
    "digest": "sha256:1e0dd84d670315587df929c161920fca3ffe7ef5f285ddfa7cbeab96aa52d72c",
    "run_id": "28826217268",
    "run_number": 213,
    "run_url": "https://github.com/\\lmthing/lmthing/actions/runs/28826217268",
    "status": "completed",
    "conclusion": "success",
    "updated_at": "2026-07-06T22:02:09.866567+00:00"
  },
  {
    "image": "social",
    "sha": "c9e53f0",
    "digest": "sha256:b8568e3b07c93eecc1b5594127dd794c77ffcf7b7fa42836e907d56cae4de9cb",
    "run_id": "28826217268",
    "run_number": 213,
    "run_url": "https://github.com/\\lmthing/lmthing/actions/runs/28826217268",
    "status": "completed",
    "conclusion": "success",
    "updated_at": "2026-07-06T22:02:17.497526+00:00"
  },
  {
    "image": "blog",
    "sha": "c9e53f0",
    "digest": "sha256:226b4865a104311f37364aa4e774574cf8fd014a1d1b9881c4edddd981f04fb5",
    "run_id": "28826217268",
    "run_number": 213,
    "run_url": "https://github.com/\\lmthing/lmthing/actions/runs/28826217268",
    "status": "completed",
    "conclusion": "success",
    "updated_at": "2026-07-06T22:01:57.877914+00:00"
  },
  {
    "image": "store",
    "sha": "c9e53f0",
    "digest": "sha256:1d3ddff3fd309af9b10d5bd135418697f8201143df6d38f58726136adf6b5a8b",
    "run_id": "28826217268",
    "run_number": 213,
    "run_url": "https://github.com/\\lmthing/lmthing/actions/runs/28826217268",
    "status": "completed",
    "conclusion": "success",
    "updated_at": "2026-07-06T22:02:16.985964+00:00"
  },
  {
    "image": "computer",
    "sha": "c9e53f0",
    "digest": "sha256:765d8718ff95bee965d74f40d8a5ce50389955ecdecc415302ae25f4b21548bb",
    "run_id": "28826217268",
    "run_number": 213,
    "run_url": "https://github.com/\\lmthing/lmthing/actions/runs/28826217268",
    "status": "completed",
    "conclusion": "success",
    "updated_at": "2026-07-06T22:02:02.842040+00:00"
  },
  {
    "image": "com",
    "sha": "c9e53f0",
    "digest": "sha256:e50c0630247f7aee92943043f96149971cac86903b9502bed3052f040d84e0c4",
    "run_id": "28826217268",
    "run_number": 213,
    "run_url": "https://github.com/\\lmthing/lmthing/actions/runs/28826217268",
    "status": "completed",
    "conclusion": "success",
    "updated_at": "2026-07-06T22:01:53.872582+00:00"
  },
  {
    "image": "chat",
    "sha": "c9e53f0",
    "digest": "sha256:3a42e581f8b3c8218a0555abe8c3989f5454d4fc124b5d8e5d1d723fd4c9f9cf",
    "run_id": "28826217268",
    "run_number": 213,
    "run_url": "https://github.com/\\lmthing/lmthing/actions/runs/28826217268",
    "status": "completed",
    "conclusion": "success",
    "updated_at": "2026-07-06T22:02:01.515886+00:00"
  },
  {
    "image": "casa",
    "sha": "c9e53f0",
    "digest": "sha256:ad2a60142e7f8fc9c1c18ef034c40cf7d0dde77972b705120aea6d4e913f3c2d",
    "run_id": "28826217268",
    "run_number": 213,
    "run_url": "https://github.com/\\lmthing/lmthing/actions/runs/28826217268",
    "status": "completed",
    "conclusion": "success",
    "updated_at": "2026-07-06T22:01:54.531644+00:00"
  },
  {
    "image": "gateway",
    "sha": "c9e53f0",
    "digest": "sha256:f280527065aa4e1065cb7b7a515db507b3a794e02ff2dbfd8a765997905815b8",
    "run_id": "28826217268",
    "run_number": 213,
    "run_url": "https://github.com/\\lmthing/lmthing/actions/runs/28826217268",
    "status": "completed",
    "conclusion": "success",
    "updated_at": "2026-07-06T22:01:32.039291+00:00"
  },
  {
    "image": "compute",
    "sha": "c9e53f0",
    "digest": "sha256:8c950d85d70da3699b8b066804e3da915ab793c7200b7abc986a54223f8cabfc",
    "run_id": "28826217268",
    "run_number": 213,
    "run_url": "https://github.com/\\lmthing/lmthing/actions/runs/28826217268",
    "status": "completed",
    "conclusion": "success",
    "updated_at": "2026-07-06T22:02:26.894416+00:00"
  },
  {
    "image": "studio",
    "sha": "c9e53f0",
    "digest": "sha256:f599af9121d519015d0a89311b38060637d8a537d6c33d5f0e1fecaabfcb64f7",
    "run_id": "28826217268",
    "run_number": 213,
    "run_url": "https://github.com/\\lmthing/lmthing/actions/runs/28826217268",
    "status": "completed",
    "conclusion": "success",
    "updated_at": "2026-07-06T22:01:52.699460+00:00"
  },
  {
    "image": "team",
    "sha": "0939ead",
    "digest": "sha256:7964f1bca5cdc011e383a78149e017c7bc431e37a5780f5edea89c14d23dac9d",
    "run_id": "28824886172",
    "run_number": 212,
    "run_url": "https://github.com/\\lmthing/lmthing/actions/runs/28824886172",
    "status": "completed",
    "conclusion": "success",
    "updated_at": "2026-07-06T21:36:48.086888+00:00"
  },
  {
    "image": "space",
    "sha": "0939ead",
    "digest": "sha256:f934633524efc617768298a6066bd92b356dc0454fc05b0d438f7e29278fc661",
    "run_id": "28824886172",
    "run_number": 212,
    "run_url": "https://github.com/\\lmthing/lmthing/actions/runs/28824886172",
    "status": "completed",
    "conclusion": "success",
    "updated_at": "2026-07-06T21:37:10.363540+00:00"
  },
  {
    "image": "social",
    "sha": "0939ead",
    "digest": "sha256:0dbab4997ffd3b44c90a5b4479d6649afc2ebf87a073390dd808f8b8139e099f",
    "run_id": "28824886172",
    "run_number": 212,
    "run_url": "https://github.com/\\lmthing/lmthing/actions/runs/28824886172",
    "status": "completed",
    "conclusion": "success",
    "updated_at": "2026-07-06T21:36:48.544128+00:00"
  },
  {
    "image": "blog",
    "sha": "0939ead",
    "digest": "sha256:f8cd00eb8d158ea2c84831440267b69e570286ecfa3dbaccfb1d1feb0dc86d2b",
    "run_id": "28824886172",
    "run_number": 212,
    "run_url": "https://github.com/\\lmthing/lmthing/actions/runs/28824886172",
    "status": "completed",
    "conclusion": "success",
    "updated_at": "2026-07-06T21:36:50.836165+00:00"
  },
  {
    "image": "store",
    "sha": "0939ead",
    "digest": "sha256:0747959da4e5266bdda307c5f91dfbefce4e83ded305c5fc60f2aa371feb1296",
    "run_id": "28824886172",
    "run_number": 212,
    "run_url": "https://github.com/\\lmthing/lmthing/actions/runs/28824886172",
    "status": "completed",
    "conclusion": "success",
    "updated_at": "2026-07-06T21:36:57.722778+00:00"
  },
  {
    "image": "computer",
    "sha": "0939ead",
    "digest": "sha256:4342a5cc789fb183126f385fee8413e7dad0a1084f8331a39133a136161afc6e",
    "run_id": "28824886172",
    "run_number": 212,
    "run_url": "https://github.com/\\lmthing/lmthing/actions/runs/28824886172",
    "status": "completed",
    "conclusion": "success",
    "updated_at": "2026-07-06T21:36:47.865082+00:00"
  },
  {
    "image": "com",
    "sha": "0939ead",
    "digest": "sha256:541bb63a21c1689ebc7beddad2e65dfe049fcb8d3f60ef8e74599c42ff52954d",
    "run_id": "28824886172",
    "run_number": 212,
    "run_url": "https://github.com/\\lmthing/lmthing/actions/runs/28824886172",
    "status": "completed",
    "conclusion": "success",
    "updated_at": "2026-07-06T21:36:50.533424+00:00"
  },
  {
    "image": "chat",
    "sha": "0939ead",
    "digest": "sha256:309f6c8d039eebbaf27ac1e2d77cc40ec1ab8fafd808706084aedcde2d377a56",
    "run_id": "28824886172",
    "run_number": 212,
    "run_url": "https://github.com/\\lmthing/lmthing/actions/runs/28824886172",
    "status": "completed",
    "conclusion": "success",
    "updated_at": "2026-07-06T21:36:48.102273+00:00"
  },
  {
    "image": "casa",
    "sha": "0939ead",
    "digest": "sha256:1d6436a0ad9db8fee325a9aba9d2c6ddc40d7f8fd2fff28ec372b5799ac16f88",
    "run_id": "28824886172",
    "run_number": 212,
    "run_url": "https://github.com/\\lmthing/lmthing/actions/runs/28824886172",
    "status": "completed",
    "conclusion": "success",
    "updated_at": "2026-07-06T21:37:01.639134+00:00"
  },
  {
    "image": "gateway",
    "sha": "0939ead",
    "digest": "sha256:fac7544f9e18ca6d322726da3f2601431c63492fa46db219c917fe3a816d1eed",
    "run_id": "28824886172",
    "run_number": 212,
    "run_url": "https://github.com/\\lmthing/lmthing/actions/runs/28824886172",
    "status": "completed",
    "conclusion": "success",
    "updated_at": "2026-07-06T21:36:28.113744+00:00"
  },
  {
    "image": "compute",
    "sha": "0939ead",
    "digest": "sha256:fd03f8027124d9012fce129a060163f51185ac69122fc19ca114d07a1646da50",
    "run_id": "28824886172",
    "run_number": 212,
    "run_url": "https://github.com/\\lmthing/lmthing/actions/runs/28824886172",
    "status": "completed",
    "conclusion": "success",
    "updated_at": "2026-07-06T21:37:31.456852+00:00"
  },
  {
    "image": "studio",
    "sha": "0939ead",
    "digest": "sha256:9774146507ed400653baab328ef7022a1eb4d90b22aa8d4cd1b0a1d2d352420c",
    "run_id": "28824886172",
    "run_number": 212,
    "run_url": "https://github.com/\\lmthing/lmthing/actions/runs/28824886172",
    "status": "completed",
    "conclusion": "success",
    "updated_at": "2026-07-06T21:37:00.534039+00:00"
  },
  {
    "image": "team",
    "sha": "0ceda4f",
    "run_id": "28823528443",
    "run_number": 211,
    "run_url": "https://github.com/\\lmthing/lmthing/actions/runs/28823528443",
    "status": "completed",
    "conclusion": "success",
    "updated_at": "2026-07-06T21:12:00.548416+00:00"
  },
  {
    "image": "space",
    "sha": "0ceda4f",
    "run_id": "28823528443",
    "run_number": 211,
    "run_url": "https://github.com/\\lmthing/lmthing/actions/runs/28823528443",
    "status": "completed",
    "conclusion": "success",
    "updated_at": "2026-07-06T21:12:07.206726+00:00"
  },
  {
    "image": "social",
    "sha": "0ceda4f",
    "run_id": "28823528443",
    "run_number": 211,
    "run_url": "https://github.com/\\lmthing/lmthing/actions/runs/28823528443",
    "status": "completed",
    "conclusion": "success",
    "updated_at": "2026-07-06T21:12:03.766759+00:00"
  },
  {
    "image": "blog",
    "sha": "0ceda4f",
    "run_id": "28823528443",
    "run_number": 211,
    "run_url": "https://github.com/\\lmthing/lmthing/actions/runs/28823528443",
    "status": "completed",
    "conclusion": "success",
    "updated_at": "2026-07-06T21:12:43.455365+00:00"
  },
  {
    "image": "store",
    "sha": "0ceda4f",
    "run_id": "28823528443",
    "run_number": 211,
    "run_url": "https://github.com/\\lmthing/lmthing/actions/runs/28823528443",
    "status": "completed",
    "conclusion": "success",
    "updated_at": "2026-07-06T21:11:50.855477+00:00"
  },
  {
    "image": "computer",
    "sha": "0ceda4f",
    "run_id": "28823528443",
    "run_number": 211,
    "run_url": "https://github.com/\\lmthing/lmthing/actions/runs/28823528443",
    "status": "completed",
    "conclusion": "success",
    "updated_at": "2026-07-06T21:12:16.149651+00:00"
  },
  {
    "image": "com",
    "sha": "0ceda4f",
    "run_id": "28823528443",
    "run_number": 211,
    "run_url": "https://github.com/\\lmthing/lmthing/actions/runs/28823528443",
    "status": "completed",
    "conclusion": "success",
    "updated_at": "2026-07-06T21:11:52.599094+00:00"
  },
  {
    "image": "chat",
    "sha": "0ceda4f",
    "run_id": "28823528443",
    "run_number": 211,
    "run_url": "https://github.com/\\lmthing/lmthing/actions/runs/28823528443",
    "status": "completed",
    "conclusion": "success",
    "updated_at": "2026-07-06T21:12:01.674134+00:00"
  },
  {
    "image": "casa",
    "sha": "0ceda4f",
    "run_id": "28823528443",
    "run_number": 211,
    "run_url": "https://github.com/\\lmthing/lmthing/actions/runs/28823528443",
    "status": "completed",
    "conclusion": "success",
    "updated_at": "2026-07-06T21:11:52.406776+00:00"
  },
  {
    "image": "compute",
    "sha": "0ceda4f",
    "run_id": "28823528443",
    "run_number": 211,
    "run_url": "https://github.com/\\lmthing/lmthing/actions/runs/28823528443",
    "status": "completed",
    "conclusion": "success",
    "updated_at": "2026-07-06T21:12:48.094940+00:00"
  },
  {
    "image": "studio",
    "sha": "0ceda4f",
    "run_id": "28823528443",
    "run_number": 211,
    "run_url": "https://github.com/\\lmthing/lmthing/actions/runs/28823528443",
    "status": "completed",
    "conclusion": "success",
    "updated_at": "2026-07-06T21:12:02.860024+00:00"
  },
  {
    "image": "team",
    "sha": "e87ea91",
    "run_id": "28822724135",
    "run_number": 210,
    "run_url": "https://github.com/\\lmthing/lmthing/actions/runs/28822724135",
    "status": "completed",
    "conclusion": "success",
    "updated_at": "2026-07-06T20:58:20.345089+00:00"
  }
]