{
  "scenario": "06-tanzania",
  "project": "tanzania-trip",
  "ranSteps": 2,
  "ofSteps": 18,
  "sessionStats": {
    "events": 1609,
    "llmCalls": 109,
    "tokens": {
      "in": 442950,
      "out": 56409
    },
    "errors": 5,
    "unrecoveredErrors": 0,
    "delegates": [
      "system-vision/vision",
      "system-files/dispatch",
      "system-files/reader",
      "system-files/sheet",
      "system-architect/architect/synthesize_and_run",
      "system-architect/architect/synthesize_and_run",
      "system-architect/architect/synthesize_and_run",
      "system-appbuilder/automator/build_live_project"
    ],
    "yieldKinds": [
      "delegate",
      "loadKnowledge",
      "readDocument",
      "inspect",
      "tasklist",
      "registerSpace"
    ]
  },
  "outDir": "/home/vasilis/LMTHING/lmthing/automation/instances/scenario-campaign/rounds/2/06-tanzania",
  "finishedAt": "2026-07-16T18:46:06.586Z"
}